dilib/__init__.py
dilib/config.py
dilib/container.py
dilib/errors.py
dilib/py.typed
dilib/specs.py
dilib/utils.py
dilib/version.py
dilib/experimental/__init__.py
dilib/experimental/core.py
dilib/experimental/tests/__init__.py
dilib/experimental/tests/test_core.py
dilib/tests/__init__.py
dilib/tests/test_config.py
dilib/tests/test_container.py
dilib/tests/test_specs.py
dilib-1.1.0.dist-info/METADATA
dilib-1.1.0.dist-info/WHEEL
dilib-1.1.0.dist-info/licenses/LICENSE
dilib-1.1.0.dist-info/RECORD
