Metadata-Version: 2.4
Name: dilib
Version: 1.1.0
Summary: Dependency injection (DI) library for Python
Project-URL: Homepage, https://github.com/ansatzcapital/dilib
Project-URL: Documentation, https://ansatzcapital.github.io/dilib
Project-URL: Packaging, https://pypi.org/project/dilib
Project-URL: Source, https://github.com/ansatzcapital/dilib
Project-URL: Tracker, https://github.com/ansatzcapital/dilib/issues
License:                                  Apache License
License-File: LICENSE
Keywords: dependency injection,design patterns,di,inversion of control,ioc
Classifier: Development Status :: 5 - Production/Stable
Classifier: Intended Audience :: Developers
Classifier: Operating System :: OS Independent
Classifier: Programming Language :: Python :: 3.8
Classifier: Programming Language :: Python :: 3.9
Classifier: Programming Language :: Python :: 3.10
Classifier: Programming Language :: Python :: 3.11
Classifier: Programming Language :: Python :: 3.12
Classifier: Programming Language :: Python :: 3.13
Classifier: Programming Language :: Python :: 3.14
Classifier: Programming Language :: Python :: Implementation :: CPython
Classifier: Programming Language :: Python :: Implementation :: PyPy
Classifier: Topic :: Software Development :: Libraries
Classifier: Topic :: Utilities
Requires-Python: >=3.8
Requires-Dist: typing-extensions>=4.4.0
